icaclswrap/__init__.py
icaclswrap/foldertool.py
icaclswrap/rights.py
icaclswrap-0.2.0.dist-info/AUTHORS.rst
icaclswrap-0.2.0.dist-info/LICENSE
icaclswrap-0.2.0.dist-info/METADATA
icaclswrap-0.2.0.dist-info/WHEEL
icaclswrap-0.2.0.dist-info/entry_points.txt
icaclswrap-0.2.0.dist-info/top_level.txt
icaclswrap-0.2.0.dist-info/RECORD
