Metadata-Version: 2.1
Name: icaclswrap
Version: 0.2.0
Summary: Windows ACL permissions management through wrapping windows executable icacls
Home-page: https://github.com/sjoerdk/icaclswrap
Author: Sjoerd Kerkstra
Author-email: sjoerd.kerkstra@radboudumc.nl
License: MIT license
Keywords: icaclswrap
Platform: UNKNOWN
Classifier: Development Status :: 2 - Pre-Alpha
Classifier: Intended Audience :: Developers
Classifier: License :: OSI Approved :: MIT License
Classifier: Natural Language :: English
Classifier: Programming Language :: Python :: 3.6
Requires-Dist: Click (>=6.0)
